melplot.py
melplot-0.1.0.dev2.dist-info/entry_points.txt
melplot-0.1.0.dev2.dist-info/LICENSE
melplot-0.1.0.dev2.dist-info/WHEEL
melplot-0.1.0.dev2.dist-info/METADATA
melplot-0.1.0.dev2.dist-info/RECORD
