Metadata-Version: 2.1
Name: melplot
Version: 0.1.0.dev2
Summary: Melodeon layout diagrams
Author-email: Zachary Moon <zmoon92@gmail.com>
Requires-Python: ~=3.7
Classifier: License :: OSI Approved :: MIT License
Requires-Dist: matplotlib
Requires-Dist: numpy
Requires-Dist: rich ; extra == "cli"
Requires-Dist: typer ; extra == "cli"
Requires-Dist: ipython ; extra == "dev"
Requires-Dist: mypy ; extra == "test"
Project-URL: Home, https://github.com/zmoon/melplot
Provides-Extra: cli
Provides-Extra: dev
Provides-Extra: test
